[{"place_id": 70736678, "licence": "Data \u00a9 OpenStreetMap contributors, ODbL 1.0. https://osm.org/copyright", "osm_type": "node", "osm_id": 6723136698, "boundingbox": ["46.5212612", "46.5213612", "26.1778501", "26.1779501"], "lat": "46.5213112", "lon": "26.1779001", "display_name": "\u0218coala Gimnazial\u0103 \u201eIoana Radu Rosetii\u201d Brusturoasa, 1, Strada Pompierilor, Cuchini\u0219, Brusturoasa, Bac\u0103u, 607075, Romania", "class": "amenity", "type": "school", "importance": 0.10000999999999996, "icon": "https://nominatim.openstreetmap.org/ui/mapicons/education_school.p.20.png"}]